hackilnge/__init__.py
hackilnge/main.py
hackilnge-0.0.4.dist-info/METADATA
hackilnge-0.0.4.dist-info/WHEEL
hackilnge-0.0.4.dist-info/top_level.txt
hackilnge-0.0.4.dist-info/RECORD
