Metadata-Version: 2.1
Name: hackilnge
Version: 0.0.4
Summary: PYPI tutorial package creation written by TeddyNote
Home-page: https://github.com/jst7501
Author: LV_1_HAEIL
Author-email: cfku0172@gmail.com
Keywords: HAEIL
Classifier: Programming Language :: Python :: 3.6
Classifier: Programming Language :: Python :: 3.7
Classifier: Programming Language :: Python :: 3.8
Classifier: Programming Language :: Python :: 3.9
Requires-Python: >=3.6
Requires-Dist: halo
Requires-Dist: tqdm
